omnetinireader/__init__.py
omnetinireader/config_parser.py
omnetinireader/version.py
omnetinireader/tests/__init__.py
omnetinireader/tests/test_config_parser.py
omnetinireader/tests/dir1/__init__.py
omnetinireader/tests/dir2/__init__.py
omnetinireader-1.8.2.dist-info/LICENSE
omnetinireader-1.8.2.dist-info/METADATA
omnetinireader-1.8.2.dist-info/WHEEL
omnetinireader-1.8.2.dist-info/top_level.txt
omnetinireader-1.8.2.dist-info/RECORD
