Metadata-Version: 2.1
Name: omnetinireader
Version: 1.8.2
Summary: omnetinireader is a Python package that reads omnetpp .ini files.
Home-page: https://sam-dev.cs.hm.edu/rover/omnet-file-reader
Author: crownet development team
Author-email: stefan_schuhbaeck@hm.edu
License: MIT
Keywords: OMNeT++, input
Platform: UNKNOWN
Classifier: Intended Audience :: Science/Research
Classifier: License :: OSI Approved :: MIT License
Classifier: Operating System :: Unix
Classifier: Programming Language :: Python :: 3 :: Only
Classifier: Topic :: Scientific/Engineering
Requires-Python: >=3.8
License-File: LICENSE
